neon_stt_plugin_nemo/__init__.py
neon_stt_plugin_nemo-0.1.0.dist-info/LICENSE.md
neon_stt_plugin_nemo-0.1.0.dist-info/METADATA
neon_stt_plugin_nemo-0.1.0.dist-info/WHEEL
neon_stt_plugin_nemo-0.1.0.dist-info/entry_points.txt
neon_stt_plugin_nemo-0.1.0.dist-info/top_level.txt
neon_stt_plugin_nemo-0.1.0.dist-info/zip-safe
neon_stt_plugin_nemo-0.1.0.dist-info/RECORD
