Metadata-Version: 2.1
Name: neon-stt-plugin-nemo
Version: 0.1.0
Summary: Nemo STT plugin for Neon
Home-page: https://github.com/NeonGeckoCom/neon-stt-plugin-nemo
Author: Neongecko
Author-email: developers@neon.ai
License: BSD-3.0
Keywords: mycroft plugin stt
Classifier: Intended Audience :: Developers
Classifier: Topic :: Text Processing :: Linguistic
Classifier: Programming Language :: Python :: 3.8
License-File: LICENSE.md
Requires-Dist: ovos-plugin-manager>=0.0.24,~=0.0
Requires-Dist: ovos-utils>=0.0.30,~=0.0
Requires-Dist: streaming-stt-nemo~=0.3
Requires-Dist: SpeechRecognition~=3.8
Provides-Extra: docker
Requires-Dist: ovos-stt-http-server==0.0.2; extra == "docker"
